py2ng/__init__.py
py2ng-0.1.3.data/scripts/py2ng
py2ng-0.1.3.dist-info/METADATA
py2ng-0.1.3.dist-info/WHEEL
py2ng-0.1.3.dist-info/top_level.txt
py2ng-0.1.3.dist-info/RECORD
