Metadata-Version: 2.1
Name: py2ng
Version: 0.1.3
Summary: Convert Marshmallow schemas to TypeScript interfaces
Home-page: UNKNOWN
Author: Alan "AJ" Pryor, Jr.
Author-email: apryor6@gmail.com
License: UNKNOWN
Platform: UNKNOWN
Requires-Dist: Flask-RESTful (>=0.3.7)
